opentypesvg/__version__.py
opentypesvg/addsvg.py
opentypesvg/dumpsvg.py
opentypesvg/fonts2svg.py
opentypesvg/utils.py
opentypesvg-1.1.5.dist-info/LICENSE.md
opentypesvg-1.1.5.dist-info/METADATA
opentypesvg-1.1.5.dist-info/WHEEL
opentypesvg-1.1.5.dist-info/entry_points.txt
opentypesvg-1.1.5.dist-info/top_level.txt
opentypesvg-1.1.5.dist-info/RECORD
