Metadata-Version: 2.1
Name: opentypesvg
Version: 1.1.5
Summary: Tools for making OpenType-SVG fonts
Home-page: https://github.com/adobe-type-tools/opentype-svg
Author: Miguel Sousa
Author-email: msousa@adobe.com
License: MIT
Platform: Any
Requires-Python: >=3.6
Requires-Dist: fontTools[woff] (>=3.1.0)
